{
  "pdf_id": "3651738",
  "model_output": {
    "CadastralDesignation": "Stockholm Vattuormen 34",
    "InspectionDate": "2024-03",
    "MoistureDamage": {
      "mentions_garage": true,
      "mentions_källare": true,
      "mentions_roof": false,
      "mentions_balcony": true,
      "mentions_bjälklag": true,
      "mentions_facade": false
    },
    "RenovationNeeds": {
      "roof": true,
      "garage": true,
      "facade": true,
      "balcony": true,
      "källare": true,
      "bjälklag": true
    },
    "AsbestosPresence": {
      "Measured": false,
      "presence": true
    },
    "SummaryInsights": "Byggnaden har flera underhållsbehov, inklusive renovering av tak, fasad, balkonger, garage, källare och bjälklag. Asbest har identifierats i byggnaden, vilket kräver särskild uppmärksamhet. Fuktproblem har noterats i källare, balkonger och bjälklag, vilket bör åtgärdas för att förhindra ytterligare skador."
  },
  "ground_truth": {
    "CadastralDesignation": "Stockholm Vattuormen 34",
    "InspectionDate": "2024-03",
    "MoistureDamage": {
      "mentions_garage": false,
      "mentions_källare": false,
      "mentions_roof": false,
      "mentions_balcony": false,
      "mentions_bjälklag": false,
      "mentions_facade": false
    },
    "RenovationNeeds": {
      "garage": false,
      "källare": false,
      "roof": false,
      "balcony": false,
      "bjälklag": false,
      "facade": false
    },
    "AsbestosPresence": {
      "Measured": false,
      "presence": true
    }
  }
}