[
  {
    "CadastralDesignation": "Bolby 18:4",
    "InspectionDate": "2024-09",
    "MoistureDamage": {
      "mentions_garage": false,
      "mentions_källare": false,
      "mentions_roof": false,
      "mentions_balcony": false,
      "mentions_bjälklag": false,
      "mentions_facade": false
    },
    "RenovationNeeds": {
      "roof": false,
      "garage": false,
      "facade": false,
      "balcony": false,
      "källare": false,
      "bjälklag": false
    },
    "AsbestosPresence": {
      "Measured": false,
      "presence": false
    },
    "SummaryInsights": null
  },
  {
    "CadastralDesignation": "Bobby 18:4",
    "InspectionDate": false,
    "MoistureDamage": {
      "mentions_garage": false,
      "mentions_källare": false,
      "mentions_roof": false,
      "mentions_balcony": false,
      "mentions_bjälklag": false,
      "mentions_facade": false
    },
    "RenovationNeeds": {
      "roof": false,
      "garage": false,
      "facade": false,
      "balcony": false,
      "källare": false,
      "bjälklag": false
    },
    "AsbestosPresence": {
      "Measured": false,
      "presence": false
    },
    "SummaryInsights": null
  },
  {
    "CadastralDesignation": "Bolby 18:4",
    "InspectionDate": "2024-09",
    "MoistureDamage": {
      "mentions_garage": false,
      "mentions_källare": false,
      "mentions_roof": false,
      "mentions_balcony": false,
      "mentions_bjälklag": false,
      "mentions_facade": false
    },
    "RenovationNeeds": {
      "roof": false,
      "garage": false,
      "facade": false,
      "balcony": false,
      "källare": false,
      "bjälklag": false
    },
    "AsbestosPresence": {
      "Measured": false,
      "presence": false
    },
    "SummaryInsights": null
  },
  {
    "CadastralDesignation": "Bolby 18:4",
    "Inspectiondate": false,
    "MoistureDamage": {
      "mentions_garage": false,
      "mentions_källare": false,
      "mentions_roof": false,
      "mentions_balcony": false,
      "mentions_bjälklag": false,
      "mentions_facade": false
    },
    "RenovationNeeds": {
      "roof": false,
      "garage": false,
      "facade": false,
      "balcony": false,
      "källare": false,
      "bjälklag": false
    },
    "AsbestosPresence": {
      "Measured": false,
      "presence": false
    },
    "SummaryInsights": null
  },
  {
    "CadastralDesignation": "Bolby 18:4",
    "InspectionDate": false,
    "MoistureDamage": {
      "mentions_garage": false,
      "mentions_källare": false,
      "mentions_roof": false,
      "mentions_balcony": false,
      "mentions_bjälklag": false,
      "mentions_facade": false
    },
    "RenovationNeeds": {
      "roof": false,
      "garage": false,
      "facade": false,
      "balcony": false,
      "källare": false,
      "bjälklag": false
    },
    "AsbestosPresence": {
      "Measured": false,
      "presence": false
    },
    "SummaryInsights": null
  },
  {
    "CadastralDesignation": "Bolby 18:4",
    "InspectionDate": false,
    "MoistureDamage": {
      "mentions_garage": false,
      "mentions_källare": false,
      "mentions_roof": false,
      "mentions_balcony": false,
      "mentions_bjälklag": false,
      "mentions_facade": false
    },
    "RenovationNeeds": {
      "roof": true,
      "garage": false,
      "facade": true,
      "balcony": false,
      "källare": false,
      "bjälklag": false
    },
    "AsbestosPresence": {
      "Measured": false,
      "presence": true
    },
    "SummaryInsights": "Fasadpanelen och plåttaket har underhållsbehov och viss rötskada har noterats. Plåttaket är äldre och teknisk livslängd är uppnådd."
  },
  {
    "CadastralDesignation": "Bolby 18:4",
    "Inspectiondate": false,
    "MoistureDamage": {
      "mentions_garage": false,
      "mentions_källare": false,
      "mentions_roof": false,
      "mentions_balcony": false,
      "mentions_bjälklag": false,
      "mentions_facade": false
    },
    "RenovationNeeds": {
      "roof": false,
      "garage": false,
      "facade": false,
      "balcony": false,
      "källare": false,
      "bjälklag": false
    },
    "AsbestosPresence": {
      "Measured": false,
      "presence": false
    },
    "SummaryInsights": "Duschrum har uppnått sin tekniska livslängd och rekommenderas för åtgärd. Fuktspärr saknas under kyl/frys och diskbänk, vilket bör åtgärdas."
  },
  {
    "CadastralDesignation": "Bolby 18:4",
    "InspectionDate": false,
    "MoistureDamage": {
      "mentions_garage": false,
      "mentions_källare": false,
      "mentions_roof": true,
      "mentions_balcony": false,
      "mentions_bjälklag": false,
      "mentions_facade": true
    },
    "RenovationNeeds": {
      "roof": true,
      "garage": false,
      "facade": true,
      "balcony": false,
      "källare": false,
      "bjälklag": false
    },
    "AsbestosPresence": {
      "Measured": false,
      "presence": true
    },
    "SummaryInsights": "Fasadpanel och yttertak bedöms vara äldre och i risk för fuktrelaterade skador, åtgärder för takets plåtskruvar rekommenderas. Eternit i grundplintar innehåller asbest och kräver fackmannamässig hantering vid rivning."
  },
  {
    "CadastralDesignation": "Bolby 18:4",
    "InspectionDate": "2024-09",
    "MoistureDamage": {
      "mentions_garage": false,
      "mentions_källare": false,
      "mentions_roof": false,
      "mentions_balcony": false,
      "mentions_bjälklag": false,
      "mentions_facade": false
    },
    "RenovationNeeds": {
      "roof": false,
      "garage": false,
      "facade": false,
      "balcony": false,
      "källare": false,
      "bjälklag": false
    },
    "AsbestosPresence": {
      "Measured": false,
      "presence": false
    },
    "SummaryInsights": null
  }
]